rocketloghandler/__init__.py
rocketloghandler/rocketloghandler.py
rocketloghandler-0.1.1.dist-info/LICENSE
rocketloghandler-0.1.1.dist-info/METADATA
rocketloghandler-0.1.1.dist-info/WHEEL
rocketloghandler-0.1.1.dist-info/top_level.txt
rocketloghandler-0.1.1.dist-info/RECORD
