Metadata-Version: 2.1
Name: rocketloghandler
Version: 0.1.1
Summary: Send python logs to RocketChat server.
Home-page: https://mygit.th-deg.de/fwahl/rocketloghandler
Author: Florian Wahl
Author-email: florian.wahl@gmail.com
License: MIT
Platform: UNKNOWN
Requires-Dist: rocketchat-API (>=0.6.34)
